pecli/__init__.py
pecli/main.py
pecli/data/PeID.yar
pecli/data/yara-crypto.yar
pecli/lib/display.py
pecli/lib/dotnet_guid.py
pecli/lib/richpe.py
pecli/lib/utils.py
pecli/plugins/__init__.py
pecli/plugins/base.py
pecli/plugins/check.py
pecli/plugins/checksize.py
pecli/plugins/crypto.py
pecli/plugins/dump.py
pecli/plugins/info.py
pecli/plugins/richpe.py
pecli/plugins/search.py
pecli/plugins/shell.py
pecli/plugins/sig.py
pecli/plugins/strings.py
pecli/plugins/vt.py
pecli-0.1.4.dist-info/LICENSE
pecli-0.1.4.dist-info/METADATA
pecli-0.1.4.dist-info/WHEEL
pecli-0.1.4.dist-info/entry_points.txt
pecli-0.1.4.dist-info/top_level.txt
pecli-0.1.4.dist-info/RECORD
