Metadata-Version: 2.1
Name: pecli
Version: 0.1.4
Summary: Another PE info tool
Home-page: https://github.com/Te-k/pecli
Author: Tek
Author-email: tek@randhome.io
License: MIT
Keywords: malware
Platform: UNKNOWN
Classifier: Programming Language :: Python :: 3
Classifier: License :: OSI Approved :: MIT License
Classifier: Operating System :: OS Independent
Requires-Python: >=3.5
Requires-Dist: pefile
Requires-Dist: yara-python
Requires-Dist: python-magic
Requires-Dist: ipython
Requires-Dist: virustotal-api (==1.1.11)
